Metadata-Version: 2.1
Name: tea-xyz2
Version: 0.0.1
Summary: A simple package for https://app.tea.xyz/
Home-page: https://github.com/madest92/tea-xyz2
Author: Alex
Author-email: madest92@mail.com
Project-URL: Homepage, https://github.com/madest92/tea-xyz2
Project-URL: Source, https://github.com/madest92/tea-xyz2
Classifier: License :: OSI Approved :: MIT License
Classifier: Programming Language :: Python :: 3
Requires-Python: >=3.6
Requires-Dist: requests>=2.20.0
